noveum_api_client/__init__.py
noveum_api_client/client.py
noveum_api_client/constants.py
noveum_api_client/errors.py
noveum_api_client/noveum_client.py
noveum_api_client/py.typed
noveum_api_client/types.py
noveum_api_client/api/__init__.py
noveum_api_client/api/audio/__init__.py
noveum_api_client/api/audio/delete_api_v1_audio_by_id.py
noveum_api_client/api/audio/get_api_v1_audio.py
noveum_api_client/api/audio/get_api_v1_audio_by_id.py
noveum_api_client/api/audio/get_api_v1_audio_by_id_serve.py
noveum_api_client/api/audio/post_api_v1_audio.py
noveum_api_client/api/datasets/__init__.py
noveum_api_client/api/datasets/delete_api_v1_datasets_by_dataset_slug_items.py
noveum_api_client/api/datasets/delete_api_v1_datasets_by_dataset_slug_items_by_item_id.py
noveum_api_client/api/datasets/delete_api_v1_datasets_by_slug.py
noveum_api_client/api/datasets/get_api_v1_datasets.py
noveum_api_client/api/datasets/get_api_v1_datasets_by_dataset_slug_items.py
noveum_api_client/api/datasets/get_api_v1_datasets_by_dataset_slug_items_by_item_id.py
noveum_api_client/api/datasets/get_api_v1_datasets_by_dataset_slug_versions.py
noveum_api_client/api/datasets/get_api_v1_datasets_by_dataset_slug_versions_by_version.py
noveum_api_client/api/datasets/get_api_v1_datasets_by_dataset_slug_versions_diff.py
noveum_api_client/api/datasets/get_api_v1_datasets_by_slug.py
noveum_api_client/api/datasets/post_api_v1_datasets.py
noveum_api_client/api/datasets/post_api_v1_datasets_by_dataset_slug_items.py
noveum_api_client/api/datasets/post_api_v1_datasets_by_dataset_slug_versions.py
noveum_api_client/api/datasets/post_api_v1_datasets_by_dataset_slug_versions_publish.py
noveum_api_client/api/datasets/put_api_v1_datasets_by_slug.py
noveum_api_client/api/etl_jobs/__init__.py
noveum_api_client/api/etl_jobs/delete_api_v1_etl_jobs_by_id.py
noveum_api_client/api/etl_jobs/get_api_v1_etl_jobs.py
noveum_api_client/api/etl_jobs/get_api_v1_etl_jobs_by_id.py
noveum_sdk-1.1.0.dist-info/METADATA
noveum_sdk-1.1.0.dist-info/WHEEL
noveum_sdk-1.1.0.dist-info/top_level.txt
noveum_sdk-1.1.0.dist-info/RECORD
