Metadata-Version: 2.4
Name: noveum-sdk
Version: 1.1.0
Summary: Official Python SDK for the Noveum.ai API - AI/ML evaluation and testing platform
Author-email: Noveum Team <team@noveum.ai>
License: Apache-2.0
Project-URL: Homepage, https://noveum.ai
Project-URL: Repository, https://github.com/Noveum/noveum-sdk-python
Project-URL: Documentation, https://noveum.ai/docs
Project-URL: Bug Tracker, https://github.com/Noveum/noveum-sdk-python/issues
Project-URL: Changelog, https://github.com/Noveum/noveum-sdk-python/blob/main/CHANGELOG.md
Keywords: noveum,ai,ml,evaluation,testing,api,sdk,observability,llm,tracing
Classifier: Development Status :: 5 - Production/Stable
Classifier: Intended Audience :: Developers
Classifier: License :: OSI Approved :: Apache Software License
Classifier: Operating System :: OS Independent
Classifier: Programming Language :: Python :: 3
Classifier: Programming Language :: Python :: 3.10
Classifier: Programming Language :: Python :: 3.11
Classifier: Programming Language :: Python :: 3.12
Classifier: Topic :: Software Development :: Libraries :: Python Modules
Classifier: Topic :: Scientific/Engineering :: Artificial Intelligence
Requires-Python: >=3.10
Requires-Dist: httpx<0.29.0,>=0.23.0
Requires-Dist: attrs>=22.2.0
Requires-Dist: python-dateutil>=2.8.0
Provides-Extra: dev
Requires-Dist: pytest>=9.0.0; extra == "dev"
Requires-Dist: pytest-cov>=7.0.0; extra == "dev"
Requires-Dist: pytest-asyncio>=1.3.0; extra == "dev"
Requires-Dist: black>=24.0.0; extra == "dev"
Requires-Dist: isort>=5.0.0; extra == "dev"
Requires-Dist: ruff>=0.14.0; extra == "dev"
Requires-Dist: mypy>=1.5.0; extra == "dev"
Requires-Dist: types-python-dateutil>=2.8.0; extra == "dev"
Requires-Dist: bandit>=1.7.5; extra == "dev"
Requires-Dist: safety>=3.7.0; extra == "dev"
Requires-Dist: python-dotenv>=1.0.0; extra == "dev"
